packy.py
packy-0.1.4.dist-info/LICENSE
packy-0.1.4.dist-info/METADATA
packy-0.1.4.dist-info/WHEEL
packy-0.1.4.dist-info/entry_points.txt
packy-0.1.4.dist-info/top_level.txt
packy-0.1.4.dist-info/RECORD
