Metadata-Version: 2.1
Name: packy
Version: 0.1.4
Summary: Package manager for downloading packages from content providers
Home-page: https://github.com/codetent/packy
Author: codetent
License: UNKNOWN
Keywords: package CDNJS JS packet
Platform: UNKNOWN
Classifier: Development Status :: 3 - Alpha
Classifier: Programming Language :: Python :: 3.5
Classifier: Programming Language :: Python :: 3.6
Classifier: Programming Language :: Python :: 3.7
Requires-Python: >=3.5
